paddleocr/LICENSE
paddleocr/MANIFEST.in
paddleocr/README.md
paddleocr/__init__.py
paddleocr/paddleocr.py
paddleocr/fadoudou.egg-info/PKG-INFO
paddleocr/fadoudou.egg-info/SOURCES.txt
paddleocr/fadoudou.egg-info/dependency_links.txt
paddleocr/fadoudou.egg-info/entry_points.txt
paddleocr/fadoudou.egg-info/requires.txt
paddleocr/fadoudou.egg-info/top_level.txt
paddleocr/paddleocr_fagougou.egg-info/PKG-INFO
paddleocr/paddleocr_fagougou.egg-info/SOURCES.txt
paddleocr/paddleocr_fagougou.egg-info/dependency_links.txt
paddleocr/paddleocr_fagougou.egg-info/entry_points.txt
paddleocr/paddleocr_fagougou.egg-info/requires.txt
paddleocr/paddleocr_fagougou.egg-info/top_level.txt
paddleocr/ppocr/data/__init__.py
paddleocr/ppocr/data/collate_fn.py
paddleocr/ppocr/data/lmdb_dataset.py
paddleocr/ppocr/data/multi_scale_sampler.py
paddleocr/ppocr/data/pgnet_dataset.py
paddleocr/ppocr/data/pubtab_dataset.py
paddleocr/ppocr/data/simple_dataset.py
paddleocr/ppocr/data/imaug/ColorJitter.py
paddleocr/ppocr/data/imaug/__init__.py
paddleocr/ppocr/data/imaug/abinet_aug.py
paddleocr/ppocr/data/imaug/copy_paste.py
paddleocr/ppocr/data/imaug/ct_process.py
paddleocr/ppocr/data/imaug/drrg_targets.py
paddleocr/ppocr/data/imaug/east_process.py
paddleocr/ppocr/data/imaug/fce_aug.py
paddleocr/ppocr/data/imaug/fce_targets.py
paddleocr/ppocr/data/imaug/iaa_augment.py
paddleocr/ppocr/data/imaug/label_ops.py
paddleocr/ppocr/data/imaug/make_border_map.py
paddleocr/ppocr/data/imaug/make_pse_gt.py
paddleocr/ppocr/data/imaug/make_shrink_map.py
paddleocr/ppocr/data/imaug/operators.py
paddleocr/ppocr/data/imaug/pg_process.py
paddleocr/ppocr/data/imaug/randaugment.py
paddleocr/ppocr/data/imaug/random_crop_data.py
paddleocr/ppocr/data/imaug/rec_img_aug.py
paddleocr/ppocr/data/imaug/sast_process.py
paddleocr/ppocr/data/imaug/ssl_img_aug.py
paddleocr/ppocr/data/imaug/table_ops.py
paddleocr/ppocr/data/imaug/text_image_aug/__init__.py
paddleocr/ppocr/data/imaug/text_image_aug/augment.py
paddleocr/ppocr/data/imaug/text_image_aug/warp_mls.py
paddleocr/ppocr/data/imaug/vqa/__init__.py
paddleocr/ppocr/data/imaug/vqa/augment.py
paddleocr/ppocr/data/imaug/vqa/token/__init__.py
paddleocr/ppocr/data/imaug/vqa/token/vqa_re_convert.py
paddleocr/ppocr/data/imaug/vqa/token/vqa_token_chunk.py
paddleocr/ppocr/data/imaug/vqa/token/vqa_token_pad.py
paddleocr/ppocr/data/imaug/vqa/token/vqa_token_relation.py
paddleocr/ppocr/postprocess/__init__.py
paddleocr/ppocr/postprocess/cls_postprocess.py
paddleocr/ppocr/postprocess/ct_postprocess.py
paddleocr/ppocr/postprocess/db_postprocess.py
fadoudou-2.7.0.3.dist-info/LICENSE
fadoudou-2.7.0.3.dist-info/METADATA
fadoudou-2.7.0.3.dist-info/WHEEL
fadoudou-2.7.0.3.dist-info/entry_points.txt
fadoudou-2.7.0.3.dist-info/top_level.txt
fadoudou-2.7.0.3.dist-info/RECORD
